air_sans/__init__.py
air_sans/app/__init__.py
air_sans/app/core.py
air_sans/app/main.py
air_sans/app/plotly.py
air_sans/app/ui.py
air_sans/app/ui_scattering.py
air_sans/app/ui_transmission.py
air_sans/app/visualization.py
air_sans/app/vtk.py
air_sans/app/assets/__init__.py
air_sans/app/assets/plotly.png
air_sans/app/assets/vtk.png
air_sans/app/instrument/__init__.py
air_sans/app/instrument/cg2.py
air_sans/app/instrument/d11_plus.py
air_sans/app/instrument/mat_files.py
air_sans/app/instrument/det_efficiency/det1_d11_plus.mat
air_sans/app/instrument/det_efficiency/det2_d11_plus.mat
air_sans/app/instrument/det_efficiency/det3_d11_plus.mat
air_sans/app/instrument/det_mask/det1_d11_plus.mat
air_sans/app/instrument/det_mask/det2_d11_plus.mat
air_sans/app/instrument/det_mask/det3_d11_plus.mat
air_sans/app/utilities/__init__.py
air_sans/app/utilities/file_load.py
air_sans/app/utilities/file_search.py
air_sans-0.3.0.dist-info/LICENSE
air_sans-0.3.0.dist-info/METADATA
air_sans-0.3.0.dist-info/WHEEL
air_sans-0.3.0.dist-info/entry_points.txt
air_sans-0.3.0.dist-info/top_level.txt
air_sans-0.3.0.dist-info/RECORD
